{
    "MetaData": {
        "ContentFormatVersion": 4,
        "Id": "Skin02",
        "Name": "Skin02",
        "ResourcePath": "DATA/Characters/Twitch/Skins/Skin02/Skin02.inibin"
    },
    "Values": {
        "ContextualAction": {
            "RuleConfigFile": "Twitch_Base.cac"
        },
        "MeshSkin": {
            "Animations": "TwitchBase.blnd",
            "ChampionSkinID": 29002,
            "ChampionSkinName": "KaiserTwitch",
            "MaterialOverride0SubMesh": "Twitch_cheese_Mat",
            "MaterialOverride0Texture": "twitch_cheese_TX_CM.dds",
            "OverrideBoundingBox": "140.0000 160.0000 140.0000",
            "SelfIllumination": 0.7000000000000001,
            "SimpleSkin": "Twitch_Whistler_village.skn",
            "Skeleton": "Twitch_Whistler_village.skl",
            "SkinScale": 1.0,
            "SubmeshesToHide": "Twitch_Cheese_Mat",
            "Texture": "twitch_whistler_TX_CM.dds",
            "vintageCutoffDate": "2013-07-31"
        }
    }
}